apitele/__init__.py
apitele/api.py
apitele/client.py
apitele/constants.py
apitele/logging.py
apitele/types.py
apitele/update_manager.py
apitele/utils.py
apitele-1.1.4.dist-info/licenses/LICENSE
apitele-1.1.4.dist-info/METADATA
apitele-1.1.4.dist-info/WHEEL
apitele-1.1.4.dist-info/top_level.txt
apitele-1.1.4.dist-info/RECORD
