Metadata-Version: 2.4
Name: apitele
Version: 1.1.4
Author: geko1
License:                     GNU GENERAL PUBLIC LICENSE
Project-URL: Repository, https://github.com/unixtux/apitele
Requires-Python: >=3.8
License-File: LICENSE
Requires-Dist: aiohttp>=3.9.1
Requires-Dist: certifi>=2023.11.17
Requires-Dist: ujson>=5.9.0
Dynamic: license-file
